{
  "english_suite": {
    "detection_rate": "0/11 (0%)",
    "avg_latency_ms": 76.9,
    "rows": [
      {
        "text": "Transfer €84,293 from IBAN FR76 3000 6000 0112 3456 7890 189",
        "expected": [
          "FR76 3000 6000 0112 3456 7890 189"
        ],
        "detected": [],
        "hits": 0,
        "of": 1,
        "latency_ms": 277.6
      },
      {
        "text": "Vendor payment to Acme Corp, account 4532015112830366, approved by John Smith",
        "expected": [
          "Acme Corp",
          "4532015112830366",
          "John Smith"
        ],
        "detected": [],
        "hits": 0,
        "of": 3,
        "latency_ms": 36.6
      },
      {
        "text": "Cost center 4420-EMEA-CORP, GL account 6100, controller Sarah Chen",
        "expected": [
          "4420-EMEA-CORP",
          "Sarah Chen"
        ],
        "detected": [],
        "hits": 0,
        "of": 2,
        "latency_ms": 41.6
      },
      {
        "text": "Invoice INV-2026-00847 for Société Générale, SWIFT SOGEFRPP",
        "expected": [
          "Société Générale",
          "SOGEFRPP"
        ],
        "detected": [],
        "hits": 0,
        "of": 2,
        "latency_ms": 41.1
      },
      {
        "text": "Board resolution: CEO approved $2.3M acquisition, confidential until April 30",
        "expected": [
          "April 30"
        ],
        "detected": [],
        "hits": 0,
        "of": 1,
        "latency_ms": 31.6
      },
      {
        "text": "john.doe@company.fr called +33 6 12 34 56 78 re: Q1 close",
        "expected": [
          "john.doe@company.fr",
          "+33 6 12 34 56 78"
        ],
        "detected": [],
        "hits": 0,
        "of": 2,
        "latency_ms": 32.9
      }
    ]
  },
  "french_finance_suite": {
    "rows_with_detection": "0/20 (0%)",
    "avg_latency_ms": 36.2,
    "rows": [
      {
        "text": "Transfert interne vers 6837-CORP-891 pour un montant de 78709.65 EUR.",
        "ner_tags": [
          0,
          0,
          0,
          32,
          0,
          0,
          0,
          0,
          0,
          0
        ],
        "detected": [],
        "found_something": false,
        "latency_ms": 35.2
      },
      {
        "text": "Facture INV-2022-57278 de Tech SCI (SIRET 49191959045602).",
        "ner_tags": [
          0,
          0,
          0,
          33,
          35,
          0,
          0
        ],
        "detected": [],
        "found_something": false,
        "latency_ms": 32.9
      },
      {
        "text": "Contactez Lea Robert au 04 81 53 90 88 pour le dossier INV-2031-41972.",
        "ner_tags": [
          0,
          17,
          19,
          0,
          21,
          22,
          22,
          22,
          23,
          0,
          0,
          0,
          0
        ],
        "detected": [],
        "found_something": false,
        "latency_ms": 37.8
      },
      {
        "text": "Transfert interne vers 1076-EMEA-824 pour un montant de 56198.09 EUR.",
        "ner_tags": [
          0,
          0,
          0,
          32,
          0,
          0,
          0,
          0,
          0,
          0
        ],
        "detected": [],
        "found_something": false,
        "latency_ms": 37.3
      },
      {
        "text": "Règlement de 62500.65 € reçu de Finance SCI via FR76 94526 33469 N9841Z3DRGY 36.",
        "ner_tags": [
          0,
          0,
          37,
          39,
          0,
          0,
          33,
          35,
          0,
          0,
          0,
          0,
          0,
          0
        ],
        "detected": [],
        "found_something": false,
        "latency_ms": 47.0
      },
      {
        "text": "Facture INV-2039-86487 de Industries SAS (SIRET 51172600971341).",
        "ner_tags": [
          0,
          0,
          0,
          33,
          35,
          0,
          0
        ],
        "detected": [],
        "found_something": false,
        "latency_ms": 36.0
      },
      {
        "text": "Règlement de 98920.85 € reçu de Solutions SCI via FR76 95407 45336 XVW53ZWYF87 21.",
        "ner_tags": [
          0,
          0,
          37,
          39,
          0,
          0,
          33,
          35,
          0,
          0,
          0,
          0,
          0,
          0
        ],
        "detected": [],
        "found_something": false,
        "latency_ms": 41.5
      },
      {
        "text": "Facture INV-2024-12237 de Finance SARL (SIRET 24224667387521).",
        "ner_tags": [
          0,
          0,
          0,
          33,
          35,
          0,
          0
        ],
        "detected": [],
        "found_something": false,
        "latency_ms": 36.2
      },
      {
        "text": "Contactez Pierre Dupont au 03 36 02 41 89 pour le dossier INV-2100-30372.",
        "ner_tags": [
          0,
          17,
          19,
          0,
          21,
          22,
          22,
          22,
          23,
          0,
          0,
          0,
          0
        ],
        "detected": [],
        "found_something": false,
        "latency_ms": 33.1
      },
      {
        "text": "Facture INV-2038-84247 de Services SA (SIRET 76899684532177).",
        "ner_tags": [
          0,
          0,
          0,
          33,
          35,
          0,
          0
        ],
        "detected": [],
        "found_something": false,
        "latency_ms": 31.8
      },
      {
        "text": "Virement de 62 590 EUR vers l'IBAN FR76 06392 55221 W6L1E51OD7Q 65 pour Emma Thomas.",
        "ner_tags": [
          0,
          0,
          37,
          38,
          39,
          0,
          0,
          1,
          2,
          2,
          2,
          3,
          0,
          0,
          0
        ],
        "detected": [],
        "found_something": false,
        "latency_ms": 38.4
      },
      {
        "text": "Virement de 90570.86 Euros vers l'IBAN FR76 48147 35876 NT3H3ZX88WK 28 pour Emma Richard.",
        "ner_tags": [
          0,
          0,
          37,
          39,
          0,
          0,
          1,
          2,
          2,
          2,
          3,
          0,
          0,
          0
        ],
        "detected": [],
        "found_something": false,
        "latency_ms": 37.4
      },
      {
        "text": "Règlement de 35 748 Euros reçu de Solutions SARL via FR76 91766 19304 8G14ZWBBDX3 11.",
        "ner_tags": [
          0,
          0,
          37,
          38,
          39,
          0,
          0,
          33,
          35,
          0,
          0,
          0,
          0,
          0,
          0
        ],
        "detected": [],
        "found_something": false,
        "latency_ms": 35.7
      },
      {
        "text": "Contactez Pierre Robert au 03 70 79 62 82 pour le dossier INV-2069-44987.",
        "ner_tags": [
          0,
          17,
          19,
          0,
          21,
          22,
          22,
          22,
          23,
          0,
          0,
          0,
          0
        ],
        "detected": [],
        "found_something": false,
        "latency_ms": 31.8
      },
      {
        "text": "Règlement de 55 072 EUR reçu de Tech SA via FR76 51918 89411 COHSSCGGI4V 03.",
        "ner_tags": [
          0,
          0,
          37,
          38,
          39,
          0,
          0,
          33,
          35,
          0,
          0,
          0,
          0,
          0,
          0
        ],
        "detected": [],
        "found_something": false,
        "latency_ms": 35.4
      },
      {
        "text": "Contactez Jean Dupont au 05 11 57 41 21 pour le dossier INV-2075-59420.",
        "ner_tags": [
          0,
          17,
          19,
          0,
          21,
          22,
          22,
          22,
          23,
          0,
          0,
          0,
          0
        ],
        "detected": [],
        "found_something": false,
        "latency_ms": 31.0
      },
      {
        "text": "Règlement de 61 271 EUR reçu de Acme EURL via FR76 46622 61418 7KR8FMOYPSS 65.",
        "ner_tags": [
          0,
          0,
          37,
          38,
          39,
          0,
          0,
          33,
          35,
          0,
          0,
          0,
          0,
          0,
          0
        ],
        "detected": [],
        "found_something": false,
        "latency_ms": 36.0
      },
      {
        "text": "Virement de 40 317 Euros vers l'IBAN FR76 01072 95399 8TSH3D68C3Z 33 pour Pierre Dupont.",
        "ner_tags": [
          0,
          0,
          37,
          38,
          39,
          0,
          0,
          1,
          2,
          2,
          2,
          3,
          0,
          0,
          0
        ],
        "detected": [],
        "found_something": false,
        "latency_ms": 39.2
      },
      {
        "text": "Transfert interne vers 6930-CORP-460 pour un montant de 14 797 €.",
        "ner_tags": [
          0,
          0,
          0,
          32,
          0,
          0,
          0,
          0,
          0,
          0,
          0
        ],
        "detected": [],
        "found_something": false,
        "latency_ms": 36.8
      },
      {
        "text": "Contactez Pierre Richard au 02 50 34 25 27 pour le dossier INV-2049-27069.",
        "ner_tags": [
          0,
          17,
          19,
          0,
          21,
          22,
          22,
          22,
          23,
          0,
          0,
          0,
          0
        ],
        "detected": [],
        "found_something": false,
        "latency_ms": 34.5
      }
    ]
  }
}